pytractions/__init__.py
pytractions/abase.py
pytractions/base.py
pytractions/base_field.py
pytractions/catalog.py
pytractions/cli.py
pytractions/container_runner.py
pytractions/exc.py
pytractions/executor.py
pytractions/graph.py
pytractions/monitor.py
pytractions/observer.py
pytractions/pkgutils.py
pytractions/runner.py
pytractions/runner_utils.py
pytractions/stmd.py
pytractions/stmd_utils.py
pytractions/traction.py
pytractions/tractor.py
pytractions/transformations.py
pytractions/traversal.py
pytractions/types.py
pytractions/utils.py
pytractions/validators.py
pytractions/logging/__init__.py
pytractions/logging/redis.py
pytractions/web/__init__.py
pytractions/web/run.py
pytractions/web/welcome.py
pytractions/web/pages/01_fundamentals.py
pytractions/web/pages/02_user_guide.py
pytractions/web/pages/03_developer_guide.py
pytractions/web/pages/04_catalog.py
pytractions/web/pages/05_container.py
pytractions/web/pages/__init__.py
pytractions-0.0.10.dist-info/licenses/LICENSE
pytractions-0.0.10.dist-info/METADATA
pytractions-0.0.10.dist-info/WHEEL
pytractions-0.0.10.dist-info/top_level.txt
pytractions-0.0.10.dist-info/RECORD
