Metadata-Version: 2.4
Name: pytractions
Version: 0.0.10
Summary: Pytractions is python framework for modular programming.
Author-email: Jindrich Luza <jluza@redhat.com>
License: LGPL-3.0-only
Project-URL: Homepage, https://github.com/midnightercz/pytractions
Requires-Python: >=3.6
License-File: LICENSE
Requires-Dist: pyyaml
Requires-Dist: lark
Requires-Dist: jsonschema
Requires-Dist: typing_extensions
Requires-Dist: protobuf<6.0.0
Requires-Dist: ray
Dynamic: license-file
